binance_us/__init__.py
binance_us/client.py
binance_us/depthcache.py
binance_us/enums.py
binance_us/exceptions.py
binance_us/helpers.py
binance_us/streams.py
binance_us/threaded_stream.py
python_binance_us-1.0.16.dist-info/LICENSE
python_binance_us-1.0.16.dist-info/METADATA
python_binance_us-1.0.16.dist-info/WHEEL
python_binance_us-1.0.16.dist-info/top_level.txt
python_binance_us-1.0.16.dist-info/RECORD
