Metadata-Version: 2.1
Name: python-binance-us
Version: 1.0.16
Summary: Binance US REST API python implementation
Home-page: https://github.com/darkfireXXI/python-binance-us
Author: darkfireXXI
Author-email: 
License: MIT
Keywords: binance us exchange rest api bitcoin ethereum btc eth neo
Platform: UNKNOWN
Classifier: Intended Audience :: Developers
Classifier: License :: OSI Approved :: MIT License
Classifier: Operating System :: OS Independent
Classifier: Programming Language :: Python :: 3
Classifier: Programming Language :: Python :: 3.5
Classifier: Programming Language :: Python :: 3.6
Classifier: Programming Language :: Python :: 3.7
Classifier: Programming Language :: Python
Classifier: Topic :: Software Development :: Libraries :: Python Modules
Requires-Dist: requests
Requires-Dist: six
Requires-Dist: dateparser
Requires-Dist: aiohttp
Requires-Dist: ujson
Requires-Dist: websockets
